code2flowdiagram/__init__.py
code2flowdiagram/engine.py
code2flowdiagram/get_ast.js
code2flowdiagram/get_ast.php
code2flowdiagram/javascript.py
code2flowdiagram/model.py
code2flowdiagram/php.py
code2flowdiagram/python.py
code2flowdiagram/ruby.py
code2flowdiagram/graphviz/bin/ANN.dll
code2flowdiagram/graphviz/bin/acyclic.exe
code2flowdiagram/graphviz/bin/bcomps.exe
code2flowdiagram/graphviz/bin/brotlicommon.dll
code2flowdiagram/graphviz/bin/brotlidec.dll
code2flowdiagram/graphviz/bin/bz2.dll
code2flowdiagram/graphviz/bin/cairo-2.dll
code2flowdiagram/graphviz/bin/ccomps.exe
code2flowdiagram/graphviz/bin/cdt.dll
code2flowdiagram/graphviz/bin/cgraph++.dll
code2flowdiagram/graphviz/bin/cgraph.dll
code2flowdiagram/graphviz/bin/circo.exe
code2flowdiagram/graphviz/bin/cluster.exe
code2flowdiagram/graphviz/bin/concrt140.dll
code2flowdiagram/graphviz/bin/config6
code2flowdiagram/graphviz/bin/diffimg.exe
code2flowdiagram/graphviz/bin/dijkstra.exe
code2flowdiagram/graphviz/bin/dot.exe
code2flowdiagram/graphviz/bin/dot2gxl.exe
code2flowdiagram/graphviz/bin/dot_builtins.exe
code2flowdiagram/graphviz/bin/edgepaint.exe
code2flowdiagram/graphviz/bin/fdp.exe
code2flowdiagram/graphviz/bin/ffi-8.dll
code2flowdiagram/graphviz/bin/fontconfig-1.dll
code2flowdiagram/graphviz/bin/freetype.dll
code2flowdiagram/graphviz/bin/fribidi-0.dll
code2flowdiagram/graphviz/bin/gc.exe
code2flowdiagram/graphviz/bin/gdtclft.dll
code2flowdiagram/graphviz/bin/getopt.dll
code2flowdiagram/graphviz/bin/gio-2.0-0.dll
code2flowdiagram/graphviz/bin/glib-2.0-0.dll
code2flowdiagram/graphviz/bin/gml2gv.exe
code2flowdiagram/graphviz/bin/gmodule-2.0-0.dll
code2flowdiagram/graphviz/bin/gobject-2.0-0.dll
code2flowdiagram/graphviz/bin/graphml2gv.exe
code2flowdiagram/graphviz/bin/gts.dll
code2flowdiagram/graphviz/bin/gv2gml.exe
code2flowdiagram/graphviz/bin/gv2gxl.exe
code2flowdiagram/graphviz/bin/gvc++.dll
code2flowdiagram/graphviz/bin/gvc.dll
code2flowdiagram/graphviz/bin/gvcolor.exe
code2flowdiagram-1.0.2.dist-info/LICENSE
code2flowdiagram-1.0.2.dist-info/METADATA
code2flowdiagram-1.0.2.dist-info/WHEEL
code2flowdiagram-1.0.2.dist-info/entry_points.txt
code2flowdiagram-1.0.2.dist-info/top_level.txt
code2flowdiagram-1.0.2.dist-info/RECORD
