Metadata-Version: 2.1
Name: code2flowdiagram
Version: 1.0.2
Summary: Visualize your source code as DOT flowcharts
Home-page: https://github.com/KeilanEvans/code2flowdiagram
Download-URL: https://github.com/KeilanEvans/code2flowdiagram/releases
Author: Keilan Evans
License: MIT
Classifier: Natural Language :: English
Classifier: Programming Language :: Python :: 3
Classifier: License :: OSI Approved :: MIT License
Classifier: Operating System :: OS Independent
Requires-Python: >=3.6
License-File: LICENSE
